blip_inference/__init__.py
blip_inference/blip.py
blip_inference/compat.py
blip_inference/model.py
blip_inference/vit.py
blip_inference-0.1.0.dist-info/LICENSE
blip_inference-0.1.0.dist-info/METADATA
blip_inference-0.1.0.dist-info/WHEEL
blip_inference-0.1.0.dist-info/top_level.txt
blip_inference-0.1.0.dist-info/RECORD
